{
    "@context": "http://iiif.io/api/presentation/2/context.json",
    "@id": "https://nakamura196.github.io/hi/data/52/01/collection.json",
    "@type": "sc:Collection",
    "label": "『明治維新史料選集』・明治維新史料選集",
    "manifests": [
        {
            "@context": "http://iiif.io/api/presentation/2/context.json",
            "@id": "https://nakamura196.github.io/hi/data/52/01/0001.json",
            "@type": "sc:Manifest",
            "label": "『明治維新史料選集』・明治維新史料選集・1",
            "thumbnail": "https://clioimg.hi.u-tokyo.ac.jp/viewer/api/image/idata%2F850%2F8500%2F52%2F0001%2F0001_r25.jpg"
        },
        {
            "@context": "http://iiif.io/api/presentation/2/context.json",
            "@id": "https://nakamura196.github.io/hi/data/52/01/0002.json",
            "@type": "sc:Manifest",
            "label": "『明治維新史料選集』・明治維新史料選集・2",
            "thumbnail": "https://clioimg.hi.u-tokyo.ac.jp/viewer/api/image/idata%2F850%2F8500%2F52%2F0002%2F0001_r25.jpg"
        }
    ],
    "vhint": "use-thumb"
}