{
    "@context": "http://iiif.io/api/presentation/2/context.json",
    "@id": "https://nakamura196.github.io/hi/data/07/01/collection.json",
    "@type": "sc:Collection",
    "label": "『大日本近世史料』・上田藩村明細帳",
    "manifests": [
        {
            "@context": "http://iiif.io/api/presentation/2/context.json",
            "@id": "https://nakamura196.github.io/hi/data/07/01/0001.json",
            "@type": "sc:Manifest",
            "label": "『大日本近世史料』・上田藩村明細帳・1",
            "thumbnail": "https://clioimg.hi.u-tokyo.ac.jp/viewer/api/image/idata%2F850%2F8500%2F07%2F0101%2F0001_r25.jpg"
        },
        {
            "@context": "http://iiif.io/api/presentation/2/context.json",
            "@id": "https://nakamura196.github.io/hi/data/07/01/0002.json",
            "@type": "sc:Manifest",
            "label": "『大日本近世史料』・上田藩村明細帳・2",
            "thumbnail": "https://clioimg.hi.u-tokyo.ac.jp/viewer/api/image/idata%2F850%2F8500%2F07%2F0102%2F0001_r25.jpg"
        },
        {
            "@context": "http://iiif.io/api/presentation/2/context.json",
            "@id": "https://nakamura196.github.io/hi/data/07/01/0003.json",
            "@type": "sc:Manifest",
            "label": "『大日本近世史料』・上田藩村明細帳・3",
            "thumbnail": "https://clioimg.hi.u-tokyo.ac.jp/viewer/api/image/idata%2F850%2F8500%2F07%2F0103%2F0001_r25.jpg"
        }
    ],
    "vhint": "use-thumb"
}