{
    "@context": "http://iiif.io/api/presentation/2/context.json",
    "@id": "https://nakamura196.github.io/hi/data/12/01/collection.json",
    "@type": "sc:Collection",
    "label": "『明治史要』・明治史要",
    "manifests": [
        {
            "@context": "http://iiif.io/api/presentation/2/context.json",
            "@id": "https://nakamura196.github.io/hi/data/12/01/0001.json",
            "@type": "sc:Manifest",
            "label": "『明治史要』・明治史要・1"
        },
        {
            "@context": "http://iiif.io/api/presentation/2/context.json",
            "@id": "https://nakamura196.github.io/hi/data/12/01/0002.json",
            "@type": "sc:Manifest",
            "label": "『明治史要』・明治史要・2"
        }
    ]
}